NLIF/NLIF.py
NLIF/__init__.py
NLIF-0.0.5.dist-info/LICENSE
NLIF-0.0.5.dist-info/METADATA
NLIF-0.0.5.dist-info/WHEEL
NLIF-0.0.5.dist-info/top_level.txt
NLIF-0.0.5.dist-info/RECORD
