Metadata-Version: 2.1
Name: NLIF
Version: 0.0.5
Summary: using natural language as condition
Home-page: https://github.com/marmot8080/NLIF
Author: marmot8080
Author-email: marmot8080@gmail.com
Project-URL: Bug Tracker, https://github.com/marmot8080/NLIF/issues
Requires-Python: >=3.7
License-File: LICENSE
Requires-Dist: openai
